notspam/__init__.py
notspam/core.py
notspam-1.0.0.dist-info/licenses/LICENSE
tests/__init__.py
tests/test_notspam.py
notspam-1.0.0.dist-info/METADATA
notspam-1.0.0.dist-info/WHEEL
notspam-1.0.0.dist-info/top_level.txt
notspam-1.0.0.dist-info/RECORD
