Metadata-Version: 2.4
Name: notspam
Version: 1.0.0
Summary: Ultra-lightweight log wrapper that prevents duplicate logs within a specified time window
Home-page: https://github.com/tikipiya/notspam
Author: tikipiya
Author-email: s2501082@sendai-nct.jp
Project-URL: Bug Reports, https://github.com/tikipiya/notspam/issues
Project-URL: Source, https://github.com/tikipiya/notspam
Keywords: logging,spam,duplicate,suppression,wrapper,lightweight
Classifier: Development Status :: 4 - Beta
Classifier: Intended Audience :: Developers
Classifier: License :: OSI Approved :: MIT License
Classifier: Operating System :: OS Independent
Classifier: Programming Language :: Python :: 3
Classifier: Programming Language :: Python :: 3.7
Classifier: Programming Language :: Python :: 3.8
Classifier: Programming Language :: Python :: 3.9
Classifier: Programming Language :: Python :: 3.10
Classifier: Programming Language :: Python :: 3.11
Classifier: Programming Language :: Python :: 3.12
Classifier: Topic :: Software Development :: Libraries :: Python Modules
Classifier: Topic :: System :: Logging
Classifier: Topic :: Utilities
Requires-Python: >=3.7
License-File: LICENSE
Dynamic: author
Dynamic: author-email
Dynamic: classifier
Dynamic: description
Dynamic: description-content-type
Dynamic: home-page
Dynamic: keywords
Dynamic: license-file
Dynamic: project-url
Dynamic: requires-python
Dynamic: summary
